AUTHORS
CHANGELOG
INSTALL
LICENSE
MANIFEST.in
README
README.rst
THANKS
TODO
setup.cfg
setup.py
doc/3rd-party-apps.rst
doc/Makefile
doc/admin-screenshot1.png
doc/changelog.rst
doc/commands.rst
doc/conf.py
doc/contributions.rst
doc/display-content.rst
doc/gerbi.png
doc/index.rst
doc/installation.rst
doc/introduction.rst
doc/navigation-template-tags.rst
doc/page-api.rst
doc/placeholders.rst
doc/settings-list.rst
doc/images/ckeditor_placeholder.png
doc/images/rte_light.png
doc/sphinx_rtd_theme/__init__.py
doc/sphinx_rtd_theme/breadcrumbs.html
doc/sphinx_rtd_theme/footer.html
doc/sphinx_rtd_theme/layout.html
doc/sphinx_rtd_theme/layout_old.html
doc/sphinx_rtd_theme/search.html
doc/sphinx_rtd_theme/searchbox.html
doc/sphinx_rtd_theme/theme.conf
doc/sphinx_rtd_theme/versions.html
doc/sphinx_rtd_theme/static/css/badge_only.css
doc/sphinx_rtd_theme/static/css/badge_only.css.map
doc/sphinx_rtd_theme/static/css/theme.css
doc/sphinx_rtd_theme/static/css/theme.css.map
doc/sphinx_rtd_theme/static/fonts/FontAwesome.otf
doc/sphinx_rtd_theme/static/fonts/Inconsolata-Bold.ttf
doc/sphinx_rtd_theme/static/fonts/Inconsolata.ttf
doc/sphinx_rtd_theme/static/fonts/Lato-Bold.ttf
doc/sphinx_rtd_theme/static/fonts/Lato-Regular.ttf
doc/sphinx_rtd_theme/static/fonts/RobotoSlab-Bold.ttf
doc/sphinx_rtd_theme/static/fonts/RobotoSlab-Regular.ttf
doc/sphinx_rtd_theme/static/fonts/fontawesome-webfont.eot
doc/sphinx_rtd_theme/static/fonts/fontawesome-webfont.svg
doc/sphinx_rtd_theme/static/fonts/fontawesome-webfont.ttf
doc/sphinx_rtd_theme/static/fonts/fontawesome-webfont.woff
doc/sphinx_rtd_theme/static/js/modernizr.min.js
doc/sphinx_rtd_theme/static/js/theme.js
eti_page_cms.egg-info/PKG-INFO
eti_page_cms.egg-info/SOURCES.txt
eti_page_cms.egg-info/dependency_links.txt
eti_page_cms.egg-info/not-zip-safe
eti_page_cms.egg-info/top_level.txt
pages/__init__.py
pages/api.py
pages/app_config.py
pages/cache.py
pages/checks.py
pages/context_processors.py
pages/managers.py
pages/models.py
pages/phttp.py
pages/placeholders.py
pages/search_indexes.py
pages/serializers.py
pages/settings.py
pages/test_runner.py
pages/urlconf_registry.py
pages/urls.py
pages/utils.py
pages/views.py
