Metadata-Version: 1.1
Name: eti-page-cms
Version: 1.0.1
Summary: A tree based Django CMS application
Home-page: http://packages.python.org/django-page-cms/
Author: Thomas Saunders
Author-email: tasaunders@gmail.com
License: BSD
Download-URL: http://pypi.python.org/packages/source/d/eti-page-cms/eti-page-cms-1.0.1.tar.gz
Platform: UNKNOWN
Classifier: Development Status :: 5 - Production/Stable
Classifier: Environment :: Web Environment
Classifier: Intended Audience :: Developers
Classifier: License :: OSI Approved :: BSD License
Classifier: Operating System :: OS Independent
Classifier: Programming Language :: Python
Classifier: Framework :: Django
Classifier: Programming Language :: Python :: 2.7
Classifier: Programming Language :: Python :: 3.3
Classifier: Programming Language :: Python :: 3.4
Classifier: Programming Language :: Python :: 3.5
Classifier: Programming Language :: JavaScript
Classifier: Topic :: Internet :: WWW/HTTP :: Site Management
